tiny_vk/__init__.py
tiny_vk/bot.py
tiny_vk/ctx.py
tiny_vk/database.py
tiny_vk/exceptions.py
tiny_vk/utils.py
tiny_vk-1.1.0.dist-info/METADATA
tiny_vk-1.1.0.dist-info/WHEEL
tiny_vk-1.1.0.dist-info/RECORD
