Metadata-Version: 2.1
Name: tiny-vk
Version: 1.1.0
Summary: Сreating simple vk bots
Author: QuoNaro
Author-email: QuoNaro@mail.ru
Requires-Python: >=3.10
Classifier: Programming Language :: Python :: 3
Classifier: Programming Language :: Python :: 3.10
Classifier: Programming Language :: Python :: 3.11
Requires-Dist: requests (==2.31.0)
Requires-Dist: vk_api (==11.9.9)
